KeyisBTools/__init__.py
KeyisBTools/bytes/__init__.py
KeyisBTools/bytes/transformation.py
KeyisBTools/cryptography/KeyringBytes.py
KeyisBTools/cryptography/__init__.py
KeyisBTools/cryptography/_m.py
KeyisBTools/cryptography/hkdf.py
KeyisBTools/cryptography/sign.py
KeyisBTools/models/__init__.py
KeyisBTools/models/dataclasses.py
KeyisBTools/models/serialization.py
keyisbtools-0.0.26.dist-info/METADATA
keyisbtools-0.0.26.dist-info/WHEEL
keyisbtools-0.0.26.dist-info/top_level.txt
keyisbtools-0.0.26.dist-info/RECORD
