Metadata-Version: 2.4
Name: KeyisBTools
Version: 0.0.26
Summary: KeyisBTools
Home-page: https://github.com/KeyisB/KeyisBTools
Author: KeyisB
Author-email: keyisb.pip@gmail.com
License: GN License v1.0
Classifier: Programming Language :: Python :: 3
Classifier: Operating System :: OS Independent
Requires-Python: >=3.12
Requires-Dist: KeyisBTools
Requires-Dist: zstandard
Requires-Dist: secretstorage
Requires-Dist: msgpack
Requires-Dist: pycryptodome
Requires-Dist: cryptography
Dynamic: author
Dynamic: author-email
Dynamic: classifier
Dynamic: description
Dynamic: description-content-type
Dynamic: home-page
Dynamic: license
Dynamic: requires-dist
Dynamic: requires-python
Dynamic: summary
